print2web/__init__.py
print2web-0.0.1.dist-info/LICENSE
print2web-0.0.1.dist-info/METADATA
print2web-0.0.1.dist-info/WHEEL
print2web-0.0.1.dist-info/top_level.txt
print2web-0.0.1.dist-info/RECORD
